aieng/rag/utils/__init__.py
aieng/rag/utils/pubmed.py
aieng/rag/utils/py.typed
aieng/rag/utils/search.py
aieng_rag_utils-1.0.0.dist-info/METADATA
aieng_rag_utils-1.0.0.dist-info/WHEEL
aieng_rag_utils-1.0.0.dist-info/RECORD
